{
  "ar": "Arabic",
  "as": "Assamese",
  "bg": "Bulgarian",
  "bho": "Bhojpuri",
  "bn": "Bangla",
  "brx": "Bodo",
  "bs": "Bosnian",
  "ca": "Catalan",
  "cmn": "Chinese",
  "cs": "Czech",
  "cy": "Welsh",
  "da": "Danish",
  "de": "German",
  "doi": "Dogri",
  "el": "Greek",
  "en": "English",
  "es": "Spanish",
  "et": "Estonian",
  "eu": "Basque",
  "fa": "Persian",
  "fi": "Finnish",
  "fil": "Filipino",
  "fr": "French",
  "gl": "Galician",
  "gu": "Gujarati",
  "he": "Hebrew",
  "hi": "Hindi",
  "hr": "Croatian",
  "hu": "Hungarian",
  "id": "Indonesian",
  "is": "Icelandic",
  "it": "Italian",
  "ja": "Japanese",
  "jv": "Javanese",
  "km": "khmer",
  "kn": "Kannada",
  "kok": "Konkani",
  "ko": "Korean",
  "lt": "Lithuanian",
  "lv": "Latvia",
  "mai": "Maithili",
  "mal": "Malayalam",
  "mni": "Manipuri",
  "mr": "Marathi",
  "ms": "Malay",
  "nb": "Norwegian Bokmål",
  "ne": "Nepali",
  "nl": "Dutch",
  "od": "Odia",
  "pa": "Punjabi",
  "pl": "Polish",
  "pt": "Portuguese",
  "ro": "Romanian",
  "ru": "Russian",
  "sa": "Sanskrit",
  "sat": "Santali",
  "sd": "Sindhi",
  "si": "Sinhala",
  "sk": "Slovak",
  "sl": "Slovenian",
  "sq": "Albanese",
  "sr": "Serbian",
  "su": "Sundanese",
  "sv": "Swedish",
  "sw": "Swahili",
  "ta": "Tamil",
  "te": "Telugu",
  "th": "Thai",
  "tr": "Turkish",
  "uk": "Ukrainian",
  "ur": "Urdu",
  "vi": "Vietnamese",
  "wuu": "Shanghainese"
}